cnvfinder/__init__.py
cnvfinder/bedloader/__init__.py
cnvfinder/bedloader/bedloader.py
cnvfinder/checkmemory/__init__.py
cnvfinder/checkmemory/checkmemory.py
cnvfinder/cnvdetector/__init__.py
cnvfinder/cnvdetector/cnvdetector.py
cnvfinder/commons/__init__.py
cnvfinder/commons/commons.py
cnvfinder/data/cytoBand.txt
cnvfinder/graphics/__init__.py
cnvfinder/graphics/graphics.py
cnvfinder/ideogram/__init__.py
cnvfinder/ideogram/ideogram.py
cnvfinder/mphandler/__init__.py
cnvfinder/mphandler/mphandler.py
cnvfinder/nrrhandler/__init__.py
cnvfinder/nrrhandler/nrrhandler.py
cnvfinder/stats/__init__.py
cnvfinder/stats/stats.py
cnvfinder/tsvparser/__init__.py
cnvfinder/tsvparser/tsvparser.py
cnvfinder/utils/__init__.py
cnvfinder/utils/utils.py
cnvfinder/vcfhandler/__init__.py
cnvfinder/vcfhandler/vcfhandler.py
cnvfinder/wrapper/__init__.py
cnvfinder/wrapper/argdesc.py
cnvfinder/wrapper/command_line.py
cnvfinder/wrapper/utils.py
cnvfinder-1.0.0b5.dist-info/LICENSE
cnvfinder-1.0.0b5.dist-info/METADATA
cnvfinder-1.0.0b5.dist-info/WHEEL
cnvfinder-1.0.0b5.dist-info/entry_points.txt
cnvfinder-1.0.0b5.dist-info/top_level.txt
cnvfinder-1.0.0b5.dist-info/RECORD
